MANIFEST.in
README.md
setup.py
streamlit_current_location/__init__.py
streamlit_current_location/example.py
streamlit_current_location.egg-info/PKG-INFO
streamlit_current_location.egg-info/SOURCES.txt
streamlit_current_location.egg-info/dependency_links.txt
streamlit_current_location.egg-info/requires.txt
streamlit_current_location.egg-info/top_level.txt
streamlit_current_location/dist/index.html
streamlit_current_location/dist/index.js
streamlit_current_location/dist/index.js.map