Metadata-Version: 2.1
Name: streamlit-current-location
Version: 0.0.1
Summary: Streamlit component to get current position
Home-page: https://github.com/misogihagi/streamlit-current-location
Author: misogihagi
Author-email: hagimiso@gmail.com
License: MIT
Platform: UNKNOWN
Requires-Python: >=3.7
Provides-Extra: devel
